pyqt_transparent_centralwidget_window/__init__.py
pyqt_transparent_centralwidget_window/transparentCentralWidgetWindow.py
pyqt_transparent_centralwidget_window-0.0.13.dist-info/LICENSE
pyqt_transparent_centralwidget_window-0.0.13.dist-info/METADATA
pyqt_transparent_centralwidget_window-0.0.13.dist-info/WHEEL
pyqt_transparent_centralwidget_window-0.0.13.dist-info/top_level.txt
pyqt_transparent_centralwidget_window-0.0.13.dist-info/RECORD
