Metadata-Version: 2.1
Name: pyqt-transparent-centralwidget-window
Version: 0.0.13
Summary: PyQt window which can set the QMainWindow as main widget and make central widget of QMainWindow transparent. Simply put, frame with no image
Home-page: https://github.com/yjg30737/pyqt-transparent-centralwidget-window.git
Author: Jung Gyu Yoon
Author-email: yjg30737@gmail.com
License: MIT
License-File: LICENSE
Requires-Dist: PyQt5 >=5.15
Requires-Dist: pyqt-custom-titlebar-window >=0.0.1
